seishmc/__init__.py
seishmc/DHMC/__init__.py
seishmc/DHMC/base.py
seishmc/DHMC/dc.py
seishmc/DHMC/fmt.py
seishmc/utils/__init__.py
seishmc/utils/find_solutions.py
seishmc/visualization/__init__.py
seishmc/visualization/viz_samples_dc.py
seishmc/visualization/viz_samples_fmt.py
seishmc-0.0.1.dist-info/LICENSE
seishmc-0.0.1.dist-info/METADATA
seishmc-0.0.1.dist-info/WHEEL
seishmc-0.0.1.dist-info/top_level.txt
seishmc-0.0.1.dist-info/RECORD
